sentineltools/__init__.py
sentineltools/ai/__init__.py
sentineltools/ai/chat/__init__.py
sentineltools/ai/models/__init__.py
sentineltools/ai/models/autovae/__init__.py
sentineltools/ai/models/nextframe/__init__.py
sentineltools/ai/models/squeezenet/__init__.py
sentineltools/ai/utils/__init__.py
sentineltools/files/__init__.py
sentineltools/images/__init__.py
sentineltools/utils/__init__.py
sentineltools/utils/negex.py
sentineltools/utils/progressbar.py
sentineltools/utils/structure.py
sentineltools/utils/watch.py
sentineltools-0.13.dist-info/LICENSE
sentineltools-0.13.dist-info/METADATA
sentineltools-0.13.dist-info/WHEEL
sentineltools-0.13.dist-info/top_level.txt
sentineltools-0.13.dist-info/RECORD
