Metadata-Version: 2.1
Name: sentineltools
Version: 0.13
Summary: A collection of AI, video, image, sound, and text tools among other things. Designed for windows.
Author: Matthew Sanchez
Author-email: xxspicymelonxx@gmail.com
Classifier: Programming Language :: Python :: 3
Classifier: License :: OSI Approved :: MIT License
Classifier: Operating System :: OS Independent
Requires-Python: >=3.10
License-File: LICENSE
Requires-Dist: chatollama
Requires-Dist: diffusers
Requires-Dist: accelerate
Requires-Dist: pillow
Requires-Dist: opencv-python
Requires-Dist: numpy
